[
  {
    "runId": "90bf27c0-ca19-43f7-8050-5b0b5eda6137",
    "startedAt": "2026-02-24T05:23:59.816Z",
    "completedAt": "2026-02-24T05:23:59.817Z",
    "cycles": [],
    "totalGas": "0",
    "totalSettled": 0,
    "status": "failed",
    "error": "DEPLOYER_PRIVATE_KEY not set"
  },
  {
    "runId": "f6a3e9a7-676a-4b6d-9801-24d3e9b154e8",
    "startedAt": "2026-02-24T05:23:59.883Z",
    "completedAt": "2026-02-24T05:23:59.884Z",
    "cycles": [],
    "totalGas": "0",
    "totalSettled": 0,
    "status": "failed",
    "error": "DEPLOYER_PRIVATE_KEY not set"
  },
  {
    "runId": "6fa05a82-9830-42e2-922c-ade1c3395729",
    "startedAt": "2026-02-24T05:23:59.990Z",
    "completedAt": "2026-02-24T05:23:59.990Z",
    "cycles": [],
    "totalGas": "0",
    "totalSettled": 0,
    "status": "failed",
    "error": "DEPLOYER_PRIVATE_KEY not set"
  },
  {
    "runId": "204158f2-990c-4509-86c0-49e789e7e45f",
    "startedAt": "2026-02-24T05:23:59.998Z",
    "completedAt": "2026-02-24T05:24:00.003Z",
    "cycles": [],
    "totalGas": "0",
    "totalSettled": 0,
    "status": "failed",
    "error": "DEPLOYER_PRIVATE_KEY not set"
  },
  {
    "runId": "c70b71a8-ec19-4845-9ac6-2f5bc4b8e0a0",
    "startedAt": "2026-02-24T05:24:00.010Z",
    "completedAt": "2026-02-24T05:24:00.010Z",
    "cycles": [],
    "totalGas": "0",
    "totalSettled": 0,
    "status": "failed",
    "error": "DEPLOYER_PRIVATE_KEY not set"
  },
  {
    "runId": "380fdea8-5752-4530-9f62-4b0aad60bdfb",
    "startedAt": "2026-02-24T05:24:00.017Z",
    "completedAt": "2026-02-24T05:24:00.017Z",
    "cycles": [],
    "totalGas": "0",
    "totalSettled": 0,
    "status": "failed",
    "error": "DEPLOYER_PRIVATE_KEY not set"
  },
  {
    "runId": "0d805043-8cb0-4e1c-adeb-086a316a2d2b",
    "startedAt": "2026-02-24T05:24:00.023Z",
    "completedAt": "2026-02-24T05:24:00.024Z",
    "cycles": [],
    "totalGas": "0",
    "totalSettled": 0,
    "status": "failed",
    "error": "DEPLOYER_PRIVATE_KEY not set"
  }
]